qos_api/__init__.py
qos_api/client.py
qos_api/constants.py
qos_api/exceptions.py
qos_api/http_client.py
qos_api/models.py
qos_api/utils.py
qos_api/ws_client.py
qos_api-0.2.1.dist-info/METADATA
qos_api-0.2.1.dist-info/WHEEL
qos_api-0.2.1.dist-info/top_level.txt
qos_api-0.2.1.dist-info/RECORD
