Metadata-Version: 2.1
Name: qos-api
Version: 0.2.1
Summary: Official Python SDK for QOS Market Data API.
Home-page: https://github.com/qos-max/qos-quote-api-python-sdk
Author: QOS
Author-email: quoteos88@gmail.com
Classifier: Programming Language :: Python :: 3
Classifier: License :: OSI Approved :: MIT License
Classifier: Operating System :: OS Independent
Requires-Python: >=3.7
Requires-Dist: pydantic (>=1.8.0)
Requires-Dist: requests (>=2.25.0)
Requires-Dist: websockets (>=10.0)
